strategytrees/__init__.py
strategytrees/binary.py
strategytrees/cross.py
strategytrees/exit_type.py
strategytrees/fitness.py
strategytrees/genetic_algorithm.py
strategytrees/greater_than.py
strategytrees/leaf.py
strategytrees/less_than.py
strategytrees/member.py
strategytrees/node.py
strategytrees/models/__init__.py
strategytrees/models/property_type.py
strategytrees/models/result.py
strategytrees/models/result_property.py
strategytrees-0.12.dist-info/METADATA
strategytrees-0.12.dist-info/WHEEL
strategytrees-0.12.dist-info/top_level.txt
strategytrees-0.12.dist-info/RECORD
