Metadata-Version: 2.1
Name: strategytrees
Version: 0.12
Summary: Evolving trading strategy trees using genetic algorithm
Author: Oliver Hitchcock
Author-email: 
License: MIT
Classifier: Programming Language :: ML
Requires-Dist: pandas ==1.5.2
Requires-Dist: numpy ==1.26.3
